fso/__init__.py
fso/config.py
fso/core.py
fso/main.py
fso/observers.py
fso/utils.py
fso_cli-1.1.0.dist-info/METADATA
fso_cli-1.1.0.dist-info/WHEEL
fso_cli-1.1.0.dist-info/entry_points.txt
fso_cli-1.1.0.dist-info/top_level.txt
fso_cli-1.1.0.dist-info/RECORD
