Metadata-Version: 2.4
Name: fso-cli
Version: 1.1.0
Summary: fso (File System Organizer) - A CLI tool that automatically organizes files into categorized folders
License-Expression: MIT
Project-URL: Homepage, https://github.com/mitacheto/fso
Project-URL: Repository, https://github.com/mitacheto/fso
Keywords: cli,file-organizer,automation,cleanup
Classifier: Development Status :: 4 - Beta
Classifier: Environment :: Console
Classifier: Intended Audience :: End Users/Desktop
Classifier: Operating System :: OS Independent
Classifier: Programming Language :: Python :: 3
Classifier: Programming Language :: Python :: 3.9
Classifier: Programming Language :: Python :: 3.10
Classifier: Programming Language :: Python :: 3.11
Classifier: Programming Language :: Python :: 3.12
Classifier: Topic :: Desktop Environment :: File Managers
Classifier: Topic :: Utilities
Requires-Python: >=3.9
Requires-Dist: typer[all]>=0.9.0
Requires-Dist: rich>=13.0.0
Requires-Dist: watchdog>=3.0.0
Requires-Dist: pyyaml>=6.0
Requires-Dist: platformdirs>=4.0.0
Provides-Extra: dev
Requires-Dist: pytest>=7.0.0; extra == "dev"
Requires-Dist: pytest-cov>=4.0.0; extra == "dev"
